Metadata-Version: 2.1
Name: django-keyedcache3
Version: 1.5.4
Summary: keyedcache
Home-page: https://github.com/kunaldeo/django-keyedcache3
Author: Kunal Deo
Author-email: kunaldeo@gmail.com
License: New BSD License
Platform: any
Classifier: Development Status :: 4 - Beta
Classifier: Environment :: Web Environment
Classifier: Intended Audience :: Developers
Classifier: License :: OSI Approved :: BSD License
Classifier: Operating System :: OS Independent
Classifier: Programming Language :: Python
Classifier: Programming Language :: Python :: 3.4
Classifier: Programming Language :: Python :: 3.5
Classifier: Framework :: Django
Requires-Dist: django (>=1.8)
